{"name": "मनोरंजन", "id": 1524, "predecessors": [{"name": "संस्कृति", "id": 4525}], "successors": [{"name": "खेल", "id": 4998}, {"name": "संगीत", "id": 6788}, {"name": "नृत्य", "id": 10204}, {"name": "नाट्यकला", "id": 10824}, {"name": "कॉमिक्स", "id": 10829}, {"name": "टेलिविज़न", "id": 10830}, {"name": "पर्यटन", "id": 10831}, {"name": "रसोई", "id": 10833}, {"name": "रंगमंच", "id": 49291}, {"name": "व्यंग्य", "id": 299892}, {"name": "मीडिया_फ्रेंचाइजी", "id": 502940}, {"name": "यौन_उद्योग", "id": 777073}, {"name": "फ़िल्म_जालस्थल", "id": 537807}, {"name": "फोटोग्राफी", "id": 710686}, {"name": "हस्तशिल्प", "id": 896753}, {"name": "पालतू_पशु", "id": 532248}, {"name": "फ़िल्म", "id": 10584}, {"name": "फ़िल्म_निर्माण", "id": 23899}, {"name": "मुद्रास्फीति", "id": 943263}]}