{"name": "कशेरुक", "id": 695138, "predecessors": [{"name": "प्राणी_विज्ञान", "id": 47124}], "successors": [{"name": "पक्षी", "id": 5710}, {"name": "मछली", "id": 8285}, {"name": "सरीसृप", "id": 36860}, {"name": "स्तनधारी", "id": 48137}, {"name": "उभयचर", "id": 48256}, {"name": "कशेरुक_शारीरिकी", "id": 726215}, {"name": "विषैले_सर्प", "id": 694373}, {"name": "ओशिआनिया_के_पक्षी", "id": 726778}, {"name": "विलुप्त_स्तनधारी", "id": 433903}, {"name": "व्यायाम_कार्यिकी", "id": 939370}, {"name": "चींटीभक्षी_स्तनधारी", "id": 1295306}, {"name": "पक्षी_कुल", "id": 795136}, {"name": "आर्कटिक_के_स्तनधारी", "id": 1060257}]}