{"name": "क्रमविकासीय_जीवविज्ञान", "id": 726765, "predecessors": [{"name": "जीव_विज्ञान", "id": 9864}, {"name": "क्रम-विकास", "id": 163265}], "successors": [{"name": "व्यायाम_कार्यिकी", "id": 939370}, {"name": "वर्गानुवंशिकी", "id": 793124}, {"name": "जलचर", "id": 46741}, {"name": "जलीय_वनस्पति", "id": 796219}, {"name": "उभयचर", "id": 48256}, {"name": "मुर्दाखोर", "id": 794059}, {"name": "सर्प", "id": 694362}, {"name": "चींटीख़ोर", "id": 696040}, {"name": "शिकारी_पक्षी", "id": 795138}, {"name": "शिखर_परभक्षी", "id": 1295383}, {"name": "उड़न_गिलहरियाँ", "id": 751568}]}