{"name": "हिमाचल_प्रदेश_के_जिले", "id": 7441, "predecessors": [{"name": "भारत_के_ज़िले", "id": 509927}, {"name": "हिमाचल_प्रदेश", "id": 4977}], "successors": [{"name": "मंडी_ज़िला", "id": 42810}, {"name": "सोलन_ज़िला", "id": 72320}, {"name": "लाहौल_और_स्पीति_ज़िला", "id": 535519}, {"name": "किन्नौर_ज़िला", "id": 718681}, {"name": "काँगड़ा_ज़िला", "id": 1020166}, {"name": "कुल्लू_ज़िला", "id": 1020168}, {"name": "सिरमौर_ज़िला", "id": 1020349}, {"name": "ऊना_ज़िला", "id": 1021435}, {"name": "चंबा_ज़िला", "id": 1021436}, {"name": "शिमला_ज़िला", "id": 1021437}, {"name": "हमीरपुर_ज़िला,_हिमाचल_प्रदेश", "id": 1066566}, {"name": "किन्नौर_ज़िले_का_भूगोल", "id": 1251400}]}